Metadata-Version: 2.1
Name: django-rest-client
Version: 0.0.1
Summary: An abstract and extensible framework for building client SDKs and CLI tools for a RESTful API.
Home-page: https://github.com/certego/django-rest-client
Author: Certego S.R.L
License: UNKNOWN
Project-URL: Documentation, https://github.com/certego/django-rest-client
Project-URL: Source, https://github.com/certego/django-rest-client
Project-URL: Tracker, https://github.com/certego/django-rest-client/issues
Keywords: sdk python command line django rest framework api client coreapi
Platform: UNKNOWN
Classifier: Intended Audience :: Developers
Classifier: License :: OSI Approved :: BSD License
Classifier: Programming Language :: Python :: 3.6
Classifier: Programming Language :: Python :: 3.7
Classifier: Programming Language :: Python :: 3.8
Classifier: Programming Language :: Python :: 3.9
Classifier: Programming Language :: Python :: 3.10
Classifier: Topic :: Software Development :: Libraries :: Python Modules
Requires-Python: >=3.6
License-File: LICENSE
Requires-Dist: requests
Requires-Dist: typing-extensions
Provides-Extra: cli
Requires-Dist: requests ; extra == 'cli'
Requires-Dist: typing-extensions ; extra == 'cli'
Requires-Dist: click ; extra == 'cli'
Provides-Extra: dev
Requires-Dist: requests ; extra == 'dev'
Requires-Dist: typing-extensions ; extra == 'dev'
Requires-Dist: click ; extra == 'dev'
Requires-Dist: black (==20.8b1) ; extra == 'dev'
Requires-Dist: flake8 (==3.9.1) ; extra == 'dev'
Requires-Dist: pre-commit (==2.12.1) ; extra == 'dev'
Requires-Dist: tox (==3.23.0) ; extra == 'dev'
Requires-Dist: tox-gh-actions (==2.5.0) ; extra == 'dev'
Requires-Dist: codecov ; extra == 'dev'
Requires-Dist: coverage ; extra == 'dev'
Requires-Dist: click-creds (==0.0.3) ; extra == 'dev'
